imperio/BoxCox.py
imperio/Clusterize.py
imperio/Combinator.py
imperio/FrequencyImputation.py
imperio/Log.py
imperio/Smoothing.py
imperio/SpatialSign.py
imperio/TargetImputation.py
imperio/Whitening.py
imperio/YeoJohnson.py
imperio/ZCA.py
imperio/__init__.py
imperio/erorrs.py
imperio-0.1.5.dist-info/LICENSE.txt
imperio-0.1.5.dist-info/METADATA
imperio-0.1.5.dist-info/WHEEL
imperio-0.1.5.dist-info/top_level.txt
imperio-0.1.5.dist-info/RECORD
