Metadata-Version: 2.1
Name: imperio
Version: 0.1.5
Summary: Imperio is a python sci-kit learn inspired package for feature engineering.
Home-page: https://github.com/SigmoidAI/imperio
Author: SigmoidAI - Păpăluță Vasile, Stojoc Vladimir
Author-email: vladimir.stojoc@gmail.com
License: MIT
Download-URL: https://github.com/ScienceKot/kydavra/archive/v1.0.tar.gz
Keywords: ml,machine learning,feature engineering,python,data science
Platform: UNKNOWN
Classifier: Development Status :: 3 - Alpha
Classifier: Framework :: Jupyter
Classifier: Intended Audience :: Science/Research
Classifier: Topic :: Scientific/Engineering :: Artificial Intelligence
Classifier: Topic :: Scientific/Engineering :: Mathematics
Classifier: Topic :: Software Development :: Libraries :: Python Modules
Classifier: Topic :: Software Development :: Build Tools
Classifier: License :: OSI Approved :: MIT License
Classifier: Programming Language :: Python :: 3
Classifier: Programming Language :: Python :: 3.4
Classifier: Programming Language :: Python :: 3.5
Classifier: Programming Language :: Python :: 3.6
Classifier: Programming Language :: Python :: 3.7
Classifier: Programming Language :: Python :: 3.8
License-File: LICENSE.txt
Requires-Dist: numpy
Requires-Dist: pandas
Requires-Dist: scikit-learn
